README.md
setup.py
splax/AminoN.py
splax/__init__.py
splaxa.egg-info/PKG-INFO
splaxa.egg-info/SOURCES.txt
splaxa.egg-info/dependency_links.txt
splaxa.egg-info/requires.txt
splaxa.egg-info/top_level.txt