Metadata-Version: 2.1
Name: splaxa
Version: 1.0
Summary: A library to create Amino bots.
Home-page: https://github.com/NfrXDRA
Author: NfrXDRA
Author-email: email@gmail.com
License: MIT
Download-URL: https://github.com/NeforMan/AminoN/tree/master
Keywords: aminoapps,amino-py,amino,amino-bot,narvii,api,python,python3,python3.x,slimakoi,official
Platform: UNKNOWN
